kcshell/__init__.py
kcshell/assembler.py
kcshell/config.py
kcshell/disassembler.py
kcshell/kcshell.py
kcshell-0.0.4.dist-info/DESCRIPTION.rst
kcshell-0.0.4.dist-info/METADATA
kcshell-0.0.4.dist-info/RECORD
kcshell-0.0.4.dist-info/WHEEL
kcshell-0.0.4.dist-info/entry_points.txt
kcshell-0.0.4.dist-info/metadata.json
kcshell-0.0.4.dist-info/top_level.txt
