Metadata-Version: 2.0
Name: kcshell
Version: 0.0.4
Summary: Simple Python3 based interactive assembly/disassembly shell for various architectures powered by Keystone/Capstone.
Home-page: https://github.com/fdiskyou/kcshell
Author: Rui Reis
Author-email: rui@deniable.org
License: BSD
Keywords: assembler,disassembler
Platform: UNKNOWN
Classifier: Topic :: Security
Classifier: Topic :: Software Development :: Assemblers
Classifier: Topic :: Software Development :: Disassemblers
Classifier: Environment :: Console
Classifier: License :: OSI Approved :: MIT License
Classifier: Operating System :: OS Independent
Classifier: Programming Language :: Python :: 3
Classifier: Programming Language :: Python :: 3.3
Classifier: Programming Language :: Python :: 3.4
Classifier: Programming Language :: Python :: 3.5
Classifier: Intended Audience :: Information Technology
Classifier: Natural Language :: English
Requires-Dist: capstone
Requires-Dist: keystone-engine
